reaper_mcp_server.py
twelvetake_reaper_mcp-1.1.0.dist-info/METADATA
twelvetake_reaper_mcp-1.1.0.dist-info/WHEEL
twelvetake_reaper_mcp-1.1.0.dist-info/entry_points.txt
twelvetake_reaper_mcp-1.1.0.dist-info/licenses/LICENSE
twelvetake_reaper_mcp-1.1.0.dist-info/RECORD
