Metadata-Version: 2.4
Name: twelvetake-reaper-mcp
Version: 1.1.0
Summary: MCP server for controlling REAPER DAW - mixing, mastering, MIDI composition, and full music production
Project-URL: Homepage, https://twelvetake.com
Project-URL: Repository, https://github.com/TwelveTake-Studios/reaper-mcp
Project-URL: Issues, https://github.com/TwelveTake-Studios/reaper-mcp/issues
Project-URL: Funding, https://buymeacoffee.com/twelvetake
Author-email: TwelveTake Studios LLC <contact@twelvetake.com>
License-Expression: MIT
License-File: LICENSE
Keywords: ai,audio,claude,daw,mastering,mcp,midi,mixing,model-context-protocol,music-production,reaper
Classifier: Development Status :: 5 - Production/Stable
Classifier: Intended Audience :: Developers
Classifier: Intended Audience :: End Users/Desktop
Classifier: License :: OSI Approved :: MIT License
Classifier: Operating System :: OS Independent
Classifier: Programming Language :: Python :: 3
Classifier: Programming Language :: Python :: 3.8
Classifier: Programming Language :: Python :: 3.9
Classifier: Programming Language :: Python :: 3.10
Classifier: Programming Language :: Python :: 3.11
Classifier: Programming Language :: Python :: 3.12
Classifier: Programming Language :: Python :: 3.13
Classifier: Topic :: Multimedia :: Sound/Audio
Classifier: Topic :: Multimedia :: Sound/Audio :: Editors
Classifier: Topic :: Software Development :: Libraries :: Python Modules
Requires-Python: >=3.8
Requires-Dist: httpx>=0.25.0
Requires-Dist: mcp>=1.0.0
